[
    {
        "sa4_code_2021": "102",
        "med_tot_psnl_incom_weekly": 727
    },
    {
        "sa4_code_2021": "101",
        "med_tot_psnl_incom_weekly": 807
    },
    {
        "sa4_code_2021": "105",
        "med_tot_psnl_incom_weekly": 748
    },
    {
        "sa4_code_2021": "103",
        "med_tot_psnl_incom_weekly": 742
    },
    {
        "sa4_code_2021": "108",
        "med_tot_psnl_incom_weekly": 592
    },
    {
        "sa4_code_2021": "106",
        "med_tot_psnl_incom_weekly": 735
    },
    {
        "sa4_code_2021": "104",
        "med_tot_psnl_incom_weekly": 635
    },
    {
        "sa4_code_2021": "111",
        "med_tot_psnl_incom_weekly": 793
    },
    {
        "sa4_code_2021": "107",
        "med_tot_psnl_incom_weekly": 754
    },
    {
        "sa4_code_2021": "109",
        "med_tot_psnl_incom_weekly": 728
    },
    {
        "sa4_code_2021": "115",
        "med_tot_psnl_incom_weekly": 987
    },
    {
        "sa4_code_2021": "110",
        "med_tot_psnl_incom_weekly": 706
    },
    {
        "sa4_code_2021": "112",
        "med_tot_psnl_incom_weekly": 681
    },
    {
        "sa4_code_2021": "117",
        "med_tot_psnl_incom_weekly": 1172
    },
    {
        "sa4_code_2021": "114",
        "med_tot_psnl_incom_weekly": 688
    },
    {
        "sa4_code_2021": "113",
        "med_tot_psnl_incom_weekly": 780
    },
    {
        "sa4_code_2021": "120",
        "med_tot_psnl_incom_weekly": 1027
    },
    {
        "sa4_code_2021": "116",
        "med_tot_psnl_incom_weekly": 832
    },
    {
        "sa4_code_2021": "122",
        "med_tot_psnl_incom_weekly": 1106
    },
    {
        "sa4_code_2021": "123",
        "med_tot_psnl_incom_weekly": 802
    },
    {
        "sa4_code_2021": "118",
        "med_tot_psnl_incom_weekly": 1289
    },
    {
        "sa4_code_2021": "127",
        "med_tot_psnl_incom_weekly": 620
    },
    {
        "sa4_code_2021": "126",
        "med_tot_psnl_incom_weekly": 982
    },
    {
        "sa4_code_2021": "119",
        "med_tot_psnl_incom_weekly": 705
    },
    {
        "sa4_code_2021": "128",
        "med_tot_psnl_incom_weekly": 1016
    },
    {
        "sa4_code_2021": "203",
        "med_tot_psnl_incom_weekly": 789
    },
    {
        "sa4_code_2021": "121",
        "med_tot_psnl_incom_weekly": 1213
    },
    {
        "sa4_code_2021": "204",
        "med_tot_psnl_incom_weekly": 743
    },
    {
        "sa4_code_2021": "208",
        "med_tot_psnl_incom_weekly": 1020
    },
    {
        "sa4_code_2021": "124",
        "med_tot_psnl_incom_weekly": 852
    },
    {
        "sa4_code_2021": "209",
        "med_tot_psnl_incom_weekly": 806
    },
    {
        "sa4_code_2021": "215",
        "med_tot_psnl_incom_weekly": 691
    },
    {
        "sa4_code_2021": "125",
        "med_tot_psnl_incom_weekly": 741
    },
    {
        "sa4_code_2021": "212",
        "med_tot_psnl_incom_weekly": 746
    },
    {
        "sa4_code_2021": "217",
        "med_tot_psnl_incom_weekly": 719
    },
    {
        "sa4_code_2021": "201",
        "med_tot_psnl_incom_weekly": 705
    },
    {
        "sa4_code_2021": "213",
        "med_tot_psnl_incom_weekly": 786
    },
    {
        "sa4_code_2021": "303",
        "med_tot_psnl_incom_weekly": 872
    },
    {
        "sa4_code_2021": "202",
        "med_tot_psnl_incom_weekly": 728
    },
    {
        "sa4_code_2021": "216",
        "med_tot_psnl_incom_weekly": 681
    },
    {
        "sa4_code_2021": "304",
        "med_tot_psnl_incom_weekly": 963
    },
    {
        "sa4_code_2021": "205",
        "med_tot_psnl_incom_weekly": 657
    },
    {
        "sa4_code_2021": "308",
        "med_tot_psnl_incom_weekly": 781
    },
    {
        "sa4_code_2021": "305",
        "med_tot_psnl_incom_weekly": 1125
    },
    {
        "sa4_code_2021": "206",
        "med_tot_psnl_incom_weekly": 1130
    },
    {
        "sa4_code_2021": "312",
        "med_tot_psnl_incom_weekly": 886
    },
    {
        "sa4_code_2021": "307",
        "med_tot_psnl_incom_weekly": 687
    },
    {
        "sa4_code_2021": "207",
        "med_tot_psnl_incom_weekly": 870
    },
    {
        "sa4_code_2021": "314",
        "med_tot_psnl_incom_weekly": 883
    },
    {
        "sa4_code_2021": "317",
        "med_tot_psnl_incom_weekly": 752
    },
    {
        "sa4_code_2021": "210",
        "med_tot_psnl_incom_weekly": 731
    },
    {
        "sa4_code_2021": "401",
        "med_tot_psnl_incom_weekly": 867
    },
    {
        "sa4_code_2021": "319",
        "med_tot_psnl_incom_weekly": 556
    },
    {
        "sa4_code_2021": "211",
        "med_tot_psnl_incom_weekly": 817
    },
    {
        "sa4_code_2021": "404",
        "med_tot_psnl_incom_weekly": 760
    },
    {
        "sa4_code_2021": "402",
        "med_tot_psnl_incom_weekly": 690
    },
    {
        "sa4_code_2021": "214",
        "med_tot_psnl_incom_weekly": 784
    },
    {
        "sa4_code_2021": "502",
        "med_tot_psnl_incom_weekly": 617
    },
    {
        "sa4_code_2021": "403",
        "med_tot_psnl_incom_weekly": 764
    },
    {
        "sa4_code_2021": "301",
        "med_tot_psnl_incom_weekly": 836
    },
    {
        "sa4_code_2021": "505",
        "med_tot_psnl_incom_weekly": 857
    },
    {
        "sa4_code_2021": "405",
        "med_tot_psnl_incom_weekly": 628
    },
    {
        "sa4_code_2021": "302",
        "med_tot_psnl_incom_weekly": 928
    },
    {
        "sa4_code_2021": "509",
        "med_tot_psnl_incom_weekly": 726
    },
    {
        "sa4_code_2021": "406",
        "med_tot_psnl_incom_weekly": 754
    },
    {
        "sa4_code_2021": "306",
        "med_tot_psnl_incom_weekly": 742
    },
    {
        "sa4_code_2021": "511",
        "med_tot_psnl_incom_weekly": 933
    },
    {
        "sa4_code_2021": "503",
        "med_tot_psnl_incom_weekly": 1122
    },
    {
        "sa4_code_2021": "309",
        "med_tot_psnl_incom_weekly": 783
    },
    {
        "sa4_code_2021": "602",
        "med_tot_psnl_incom_weekly": 663
    },
    {
        "sa4_code_2021": "506",
        "med_tot_psnl_incom_weekly": 808
    },
    {
        "sa4_code_2021": "310",
        "med_tot_psnl_incom_weekly": 745
    },
    {
        "sa4_code_2021": "702",
        "med_tot_psnl_incom_weekly": 634
    },
    {
        "sa4_code_2021": "507",
        "med_tot_psnl_incom_weekly": 852
    },
    {
        "sa4_code_2021": "311",
        "med_tot_psnl_incom_weekly": 727
    },
    {
        "sa4_code_2021": "510",
        "med_tot_psnl_incom_weekly": 1412
    },
    {
        "sa4_code_2021": "313",
        "med_tot_psnl_incom_weekly": 671
    },
    {
        "sa4_code_2021": "601",
        "med_tot_psnl_incom_weekly": 776
    },
    {
        "sa4_code_2021": "315",
        "med_tot_psnl_incom_weekly": 798
    },
    {
        "sa4_code_2021": "603",
        "med_tot_psnl_incom_weekly": 618
    },
    {
        "sa4_code_2021": "316",
        "med_tot_psnl_incom_weekly": 747
    },
    {
        "sa4_code_2021": "604",
        "med_tot_psnl_incom_weekly": 638
    },
    {
        "sa4_code_2021": "318",
        "med_tot_psnl_incom_weekly": 807
    },
    {
        "sa4_code_2021": "801",
        "med_tot_psnl_incom_weekly": 1200
    },
    {
        "sa4_code_2021": "407",
        "med_tot_psnl_incom_weekly": 640
    },
    {
        "sa4_code_2021": "501",
        "med_tot_psnl_incom_weekly": 736
    },
    {
        "sa4_code_2021": "504",
        "med_tot_psnl_incom_weekly": 828
    },
    {
        "sa4_code_2021": "701",
        "med_tot_psnl_incom_weekly": 1093
    },
    {
        "sa4_code_2021": "901",
        "med_tot_psnl_incom_weekly": 906
    }
]